<?xml version="1.0" encoding="UTF-8"?>

<databaseChangeLog xmlns="http://www.liquibase.org/xml/ns/dbchangelog"
	xmlns:xsi="http://www.w3.org/2001/XMLSchema-instance" xmlns:ext="http://www.liquibase.org/xml/ns/dbchangelog-ext"
	xsi:schemaLocation="http://www.liquibase.org/xml/ns/dbchangelog 
		http://www.liquibase.org/xml/ns/dbchangelog/dbchangelog-2.0.xsd
		http://www.liquibase.org/xml/ns/dbchangelog-ext 
		http://www.liquibase.org/xml/ns/dbchangelog/dbchangelog-ext.xsd">

	<changeSet author='jon.adams' id='Add early_alert_suggestion table'>
		<createTable tableName="early_alert_suggestion">
			<column name="id" type="uuid">
				<constraints primaryKey="true" nullable="false" />
			</column>
			<column name="name" type="character varying(80)">
				<constraints nullable="false" />
			</column>
			<column name="description" type="text">
				<constraints nullable="true" />
			</column>
			<column name="created_date" type="datetime">
				<constraints nullable="false" />
			</column>
			<column name="modified_date" type="datetime" />
			<column name="created_by" type="uuid">
				<constraints nullable="false"
					foreignKeyName="early_alert_suggestion_created_by_person_id"
					references="person(id)" />
			</column>
			<column name="modified_by" type="uuid">
				<constraints nullable="true"
					foreignKeyName="early_alert_suggestion_modified_by_person_id"
					references="person(id)" />
			</column>
			<column name="object_status" type="int">
				<constraints nullable="false" />
			</column>
			<column name="sort_order" type="smallint" defaultValue="0">
				<constraints nullable="false" />
			</column>
		</createTable>

		<sql>grant all on early_alert_suggestion to ssp</sql>
		<rollback>
			<dropTable tableName="early_alert_suggestion" />
		</rollback>

		<!-- Theres a different assumption in the liquibase handling of timezones 
			on postgres. Specifying "Without" timezone -->
		<modifySql dbms="postgresql">
			<replace replace="WITH TIME ZONE" with="WITHOUT TIME ZONE" />
		</modifySql>
	</changeSet>

	<changeSet id="create reference data - early_alert_suggestion"
		author="jon.adams">
		<insert tableName="early_alert_suggestion">
			<column name="id" value="B2D11160-5056-A51A-807D9897C14BDD44" />
			<column name="name" value="Counseling Services" />
			<column name="description" value="" />
			<column name="created_date" valueDate="2012-05-03T00:00:00" />
			<column name="modified_date" valueDate="2012-05-03T00:00:00" />
			<column name="created_by" value="58ba5ee3-734e-4ae9-b9c5-943774b4de41" />
			<column name="modified_by" value="58ba5ee3-734e-4ae9-b9c5-943774b4de41" />
			<column name="object_status" value="1" />
			<column name="sort_order" value="3" />
		</insert>
		<insert tableName="early_alert_suggestion">
			<column name="id" value="B2D111FD-5056-A51A-80FE6F3344174DBE" />
			<column name="name" value="DEV Professional Tutoring" />
			<column name="description" value="" />
			<column name="created_date" valueDate="2012-05-03T00:00:00" />
			<column name="modified_date" valueDate="2012-05-03T00:00:00" />
			<column name="created_by" value="58ba5ee3-734e-4ae9-b9c5-943774b4de41" />
			<column name="modified_by" value="58ba5ee3-734e-4ae9-b9c5-943774b4de41" />
			<column name="object_status" value="1" />
			<column name="sort_order" value="9" />
		</insert>
		<insert tableName="early_alert_suggestion">
			<column name="id" value="B2D111DD-5056-A51A-8034909BD6AF80D5" />
			<column name="name" value="Disability Service Intervention" />
			<column name="description" value="" />
			<column name="created_date" valueDate="2012-05-03T00:00:00" />
			<column name="modified_date" valueDate="2012-05-03T00:00:00" />
			<column name="created_by" value="58ba5ee3-734e-4ae9-b9c5-943774b4de41" />
			<column name="modified_by" value="58ba5ee3-734e-4ae9-b9c5-943774b4de41" />
			<column name="object_status" value="1" />
			<column name="sort_order" value="7" />
		</insert>
		<insert tableName="early_alert_suggestion">
			<column name="id" value="B2D1120C-5056-A51A-80EAC779A3109F8F" />
			<column name="name" value="Other" />
			<column name="description" value="" />
			<column name="created_date" valueDate="2012-05-03T00:00:00" />
			<column name="modified_date" valueDate="2012-05-03T00:00:00" />
			<column name="created_by" value="58ba5ee3-734e-4ae9-b9c5-943774b4de41" />
			<column name="modified_by" value="58ba5ee3-734e-4ae9-b9c5-943774b4de41" />
			<column name="object_status" value="1" />
			<column name="sort_order" value="10" />
		</insert>
		<insert tableName="early_alert_suggestion">
			<column name="id" value="B2D11151-5056-A51A-80513ACDF99FEF84" />
			<column name="name" value="See Advisor or Coach" />
			<column name="description" value="" />
			<column name="created_date" valueDate="2012-05-03T00:00:00" />
			<column name="modified_date" valueDate="2012-05-03T00:00:00" />
			<column name="created_by" value="58ba5ee3-734e-4ae9-b9c5-943774b4de41" />
			<column name="modified_by" value="58ba5ee3-734e-4ae9-b9c5-943774b4de41" />
			<column name="object_status" value="1" />
			<column name="sort_order" value="2" />
		</insert>
		<insert tableName="early_alert_suggestion">
			<column name="id" value="B2D11141-5056-A51A-80C1C1250BA820F8" />
			<column name="name" value="See Instructor" />
			<column name="description" value="" />
			<column name="created_date" valueDate="2012-05-03T00:00:00" />
			<column name="modified_date" valueDate="2012-05-03T00:00:00" />
			<column name="created_by" value="58ba5ee3-734e-4ae9-b9c5-943774b4de41" />
			<column name="modified_by" value="58ba5ee3-734e-4ae9-b9c5-943774b4de41" />
			<column name="object_status" value="1" />
			<column name="sort_order" value="1" />
		</insert>
		<insert tableName="early_alert_suggestion">
			<column name="id" value="B2D11170-5056-A51A-8002B5CE9F25E2BC" />
			<column name="name" value="The Tutoring/Learning Center" />
			<column name="description" value="" />
			<column name="created_date" valueDate="2012-05-03T00:00:00" />
			<column name="modified_date" valueDate="2012-05-03T00:00:00" />
			<column name="created_by" value="58ba5ee3-734e-4ae9-b9c5-943774b4de41" />
			<column name="modified_by" value="58ba5ee3-734e-4ae9-b9c5-943774b4de41" />
			<column name="object_status" value="1" />
			<column name="sort_order" value="4" />
		</insert>
		<insert tableName="early_alert_suggestion">
			<column name="id" value="B2D111CE-5056-A51A-8017676C4D8C4F1D" />
			<column name="name" value="Tutoring Svcs (Bldg 10)" />
			<column name="description" value="" />
			<column name="created_date" valueDate="2012-05-03T00:00:00" />
			<column name="modified_date" valueDate="2012-05-03T00:00:00" />
			<column name="created_by" value="58ba5ee3-734e-4ae9-b9c5-943774b4de41" />
			<column name="modified_by" value="58ba5ee3-734e-4ae9-b9c5-943774b4de41" />
			<column name="object_status" value="1" />
			<column name="sort_order" value="6" />
		</insert>
		<insert tableName="early_alert_suggestion">
			<column name="id" value="B2D111ED-5056-A51A-80465291453E8720" />
			<column name="name" value="Withdraw" />
			<column name="description" value="" />
			<column name="created_date" valueDate="2012-05-03T00:00:00" />
			<column name="modified_date" valueDate="2012-05-03T00:00:00" />
			<column name="created_by" value="58ba5ee3-734e-4ae9-b9c5-943774b4de41" />
			<column name="modified_by" value="58ba5ee3-734e-4ae9-b9c5-943774b4de41" />
			<column name="object_status" value="1" />
			<column name="sort_order" value="8" />
		</insert>
		<insert tableName="early_alert_suggestion">
			<column name="id" value="B2D111BE-5056-A51A-8075C5A65DA17079" />
			<column name="name" value="Writing Center" />
			<column name="description" value="" />
			<column name="created_date" valueDate="2012-05-03T00:00:00" />
			<column name="modified_date" valueDate="2012-05-03T00:00:00" />
			<column name="created_by" value="58ba5ee3-734e-4ae9-b9c5-943774b4de41" />
			<column name="modified_by" value="58ba5ee3-734e-4ae9-b9c5-943774b4de41" />
			<column name="object_status" value="1" />
			<column name="sort_order" value="5" />
		</insert>
		<rollback>
			<delete tableName="early_alert_suggestion">
				<where>id='B2D11160-5056-A51A-807D9897C14BDD44'</where>
			</delete>
			<delete tableName="early_alert_suggestion">
				<where>id='B2D111FD-5056-A51A-80FE6F3344174DBE'</where>
			</delete>
			<delete tableName="early_alert_suggestion">
				<where>id='B2D111DD-5056-A51A-8034909BD6AF80D5'</where>
			</delete>
			<delete tableName="early_alert_suggestion">
				<where>id='B2D1120C-5056-A51A-80EAC779A3109F8F'</where>
			</delete>
			<delete tableName="early_alert_suggestion">
				<where>id='B2D11151-5056-A51A-80513ACDF99FEF84'</where>
			</delete>
			<delete tableName="early_alert_suggestion">
				<where>id='B2D11141-5056-A51A-80C1C1250BA820F8'</where>
			</delete>
			<delete tableName="early_alert_suggestion">
				<where>id='B2D11170-5056-A51A-8002B5CE9F25E2BC'</where>
			</delete>
			<delete tableName="early_alert_suggestion">
				<where>id='B2D111CE-5056-A51A-8017676C4D8C4F1D'</where>
			</delete>
			<delete tableName="early_alert_suggestion">
				<where>id='B2D111ED-5056-A51A-80465291453E8720'</where>
			</delete>
			<delete tableName="early_alert_suggestion">
				<where>id='B2D111BE-5056-A51A-8075C5A65DA17079'</where>
			</delete>
		</rollback>
	</changeSet>

	<changeSet author='jon.adams' id='Add early_alert_referral table'>
		<createTable tableName="early_alert_referral">
			<column name="id" type="uuid">
				<constraints primaryKey="true" nullable="false" />
			</column>
			<column name="name" type="character varying(80)">
				<constraints nullable="false" />
			</column>
			<column name="description" type="text">
				<constraints nullable="true" />
			</column>
			<column name="created_date" type="datetime">
				<constraints nullable="false" />
			</column>
			<column name="modified_date" type="datetime" />
			<column name="created_by" type="uuid">
				<constraints nullable="false"
					foreignKeyName="early_alert_referral_created_by_person_id"
					references="person(id)" />
			</column>
			<column name="modified_by" type="uuid">
				<constraints nullable="true"
					foreignKeyName="early_alert_referral_modified_by_person_id"
					references="person(id)" />
			</column>
			<column name="object_status" type="int">
				<constraints nullable="false" />
			</column>
			<column name="sort_order" type="smallint" defaultValue="0">
				<constraints nullable="false" />
			</column>
			<column name="acronym" type="character varying(80)">
				<constraints nullable="false" />
			</column>
		</createTable>

		<sql>grant all on early_alert_referral to ssp</sql>
		<rollback>
			<dropTable tableName="early_alert_referral" />
		</rollback>

		<!-- Theres a different assumption in the liquibase handling of timezones 
			on postgres. Specifying "Without" timezone -->
		<modifySql dbms="postgresql">
			<replace replace="WITH TIME ZONE" with="WITHOUT TIME ZONE" />
		</modifySql>
	</changeSet>

	<changeSet id="create reference data - early_alert_referral"
		author="jon.adams">
		<insert tableName="early_alert_referral">
			<column name="id" value="1F5729AF-0337-4E58-A001-8A9F80DBF8AA" />
			<column name="name"
				value="Answered Yes to Critical Self Help Guide Question" />
			<column name="description" value="" />
			<column name="acronym" value="SHGC" />
			<column name="created_date" valueDate="2012-05-03T00:00:00" />
			<column name="modified_date" valueDate="2012-05-03T00:00:00" />
			<column name="created_by" value="58ba5ee3-734e-4ae9-b9c5-943774b4de41" />
			<column name="modified_by" value="58ba5ee3-734e-4ae9-b9c5-943774b4de41" />
			<column name="object_status" value="1" />
			<column name="sort_order" value="9" />
		</insert>
		<insert tableName="early_alert_referral">
			<column name="id" value="300D68EF-38C2-4B7D-AD46-7874AA5D34AC" />
			<column name="name" value="Self Help Guide Threshold Exceeded" />
			<column name="description" value="" />
			<column name="acronym" value="SHGT" />
			<column name="created_date" valueDate="2012-05-03T00:00:00" />
			<column name="modified_date" valueDate="2012-05-03T00:00:00" />
			<column name="created_by" value="58ba5ee3-734e-4ae9-b9c5-943774b4de41" />
			<column name="modified_by" value="58ba5ee3-734e-4ae9-b9c5-943774b4de41" />
			<column name="object_status" value="1" />
			<column name="sort_order" value="10" />
		</insert>
		<insert tableName="early_alert_referral">
			<column name="id" value="B2D112A9-5056-A51A-8010B510525EA3A8" />
			<column name="name" value="Academic Concern" />
			<column name="description" value="" />
			<column name="acronym" value="AC" />
			<column name="created_date" valueDate="2012-05-03T00:00:00" />
			<column name="modified_date" valueDate="2012-05-03T00:00:00" />
			<column name="created_by" value="58ba5ee3-734e-4ae9-b9c5-943774b4de41" />
			<column name="modified_by" value="58ba5ee3-734e-4ae9-b9c5-943774b4de41" />
			<column name="object_status" value="1" />
			<column name="sort_order" value="1" />
		</insert>
		<insert tableName="early_alert_referral">
			<column name="id" value="B2D112B8-5056-A51A-80671FDA2849C3E5" />
			<column name="name" value="Excessive Absences" />
			<column name="description" value="" />
			<column name="acronym" value="EA" />
			<column name="created_date" valueDate="2012-05-03T00:00:00" />
			<column name="modified_date" valueDate="2012-05-03T00:00:00" />
			<column name="created_by" value="58ba5ee3-734e-4ae9-b9c5-943774b4de41" />
			<column name="modified_by" value="58ba5ee3-734e-4ae9-b9c5-943774b4de41" />
			<column name="object_status" value="1" />
			<column name="sort_order" value="2" />
		</insert>
		<insert tableName="early_alert_referral">
			<column name="id" value="B2D112C8-5056-A51A-80D5BEEC7D48CB5D" />
			<column name="name" value="Low Homework/Quizzes" />
			<column name="description" value="" />
			<column name="acronym" value="HQ" />
			<column name="created_date" valueDate="2012-05-03T00:00:00" />
			<column name="modified_date" valueDate="2012-05-03T00:00:00" />
			<column name="created_by" value="58ba5ee3-734e-4ae9-b9c5-943774b4de41" />
			<column name="modified_by" value="58ba5ee3-734e-4ae9-b9c5-943774b4de41" />
			<column name="object_status" value="1" />
			<column name="sort_order" value="3" />
		</insert>
		<insert tableName="early_alert_referral">
			<column name="id" value="B2D112D7-5056-A51A-80AA795E56155AF5" />
			<column name="name" value="Low Test Scores" />
			<column name="description" value="" />
			<column name="acronym" value="TS" />
			<column name="created_date" valueDate="2012-05-03T00:00:00" />
			<column name="modified_date" valueDate="2012-05-03T00:00:00" />
			<column name="created_by" value="58ba5ee3-734e-4ae9-b9c5-943774b4de41" />
			<column name="modified_by" value="58ba5ee3-734e-4ae9-b9c5-943774b4de41" />
			<column name="object_status" value="1" />
			<column name="sort_order" value="4" />
		</insert>
		<insert tableName="early_alert_referral">
			<column name="id" value="B2D112E7-5056-A51A-80E8A30645C463E4" />
			<column name="name" value="Never Attended" />
			<column name="description" value="" />
			<column name="acronym" value="NS" />
			<column name="created_date" valueDate="2012-05-03T00:00:00" />
			<column name="modified_date" valueDate="2012-05-03T00:00:00" />
			<column name="created_by" value="58ba5ee3-734e-4ae9-b9c5-943774b4de41" />
			<column name="modified_by" value="58ba5ee3-734e-4ae9-b9c5-943774b4de41" />
			<column name="object_status" value="1" />
			<column name="sort_order" value="5" />
		</insert>
		<insert tableName="early_alert_referral">
			<column name="id" value="B2D11316-5056-A51A-80F979421BDF08BF" />
			<column name="name" value="Personal Concern" />
			<column name="description" value="" />
			<column name="acronym" value="PE" />
			<column name="created_date" valueDate="2012-05-03T00:00:00" />
			<column name="modified_date" valueDate="2012-05-03T00:00:00" />
			<column name="created_by" value="58ba5ee3-734e-4ae9-b9c5-943774b4de41" />
			<column name="modified_by" value="58ba5ee3-734e-4ae9-b9c5-943774b4de41" />
			<column name="object_status" value="1" />
			<column name="sort_order" value="6" />
		</insert>
		<insert tableName="early_alert_referral">
			<column name="id" value="B2D11326-5056-A51A-806C79F352D0C2B2" />
			<column name="name" value="Tardiness" />
			<column name="description" value="" />
			<column name="acronym" value="TA" />
			<column name="created_date" valueDate="2012-05-03T00:00:00" />
			<column name="modified_date" valueDate="2012-05-03T00:00:00" />
			<column name="created_by" value="58ba5ee3-734e-4ae9-b9c5-943774b4de41" />
			<column name="modified_by" value="58ba5ee3-734e-4ae9-b9c5-943774b4de41" />
			<column name="object_status" value="1" />
			<column name="sort_order" value="7" />
		</insert>
		<insert tableName="early_alert_referral">
			<column name="id" value="B2D11335-5056-A51A-80EA074F8FEF94EA" />
			<column name="name" value="Other" />
			<column name="description" value="" />
			<column name="acronym" value="OT" />
			<column name="created_date" valueDate="2012-05-03T00:00:00" />
			<column name="modified_date" valueDate="2012-05-03T00:00:00" />
			<column name="created_by" value="58ba5ee3-734e-4ae9-b9c5-943774b4de41" />
			<column name="modified_by" value="58ba5ee3-734e-4ae9-b9c5-943774b4de41" />
			<column name="object_status" value="1" />
			<column name="sort_order" value="8" />
		</insert>
		<rollback>
			<delete tableName="early_alert_referral">
				<where>id='1F5729AF-0337-4E58-A001-8A9F80DBF8AA'</where>
			</delete>
			<delete tableName="early_alert_referral">
				<where>id='300D68EF-38C2-4B7D-AD46-7874AA5D34AC'</where>
			</delete>
			<delete tableName="early_alert_referral">
				<where>id='B2D112A9-5056-A51A-8010B510525EA3A8'</where>
			</delete>
			<delete tableName="early_alert_referral">
				<where>id='B2D112B8-5056-A51A-80671FDA2849C3E5'</where>
			</delete>
			<delete tableName="early_alert_referral">
				<where>id='B2D112C8-5056-A51A-80D5BEEC7D48CB5D'</where>
			</delete>
			<delete tableName="early_alert_referral">
				<where>id='B2D112D7-5056-A51A-80AA795E56155AF5'</where>
			</delete>
			<delete tableName="early_alert_referral">
				<where>id='B2D112E7-5056-A51A-80E8A30645C463E4'</where>
			</delete>
			<delete tableName="early_alert_referral">
				<where>id='B2D11316-5056-A51A-80F979421BDF08BF'</where>
			</delete>
			<delete tableName="early_alert_referral">
				<where>id='B2D11326-5056-A51A-806C79F352D0C2B2'</where>
			</delete>
			<delete tableName="early_alert_referral">
				<where>id='B2D11335-5056-A51A-80EA074F8FEF94EA'</where>
			</delete>
		</rollback>
	</changeSet>

	<changeSet author='jon.adams' id='Add early_alert_reason table'>
		<createTable tableName="early_alert_reason">
			<column name="id" type="uuid">
				<constraints primaryKey="true" nullable="false" />
			</column>
			<column name="name" type="character varying(80)">
				<constraints nullable="false" />
			</column>
			<column name="description" type="text">
				<constraints nullable="true" />
			</column>
			<column name="created_date" type="datetime">
				<constraints nullable="false" />
			</column>
			<column name="modified_date" type="datetime" />
			<column name="created_by" type="uuid">
				<constraints nullable="false"
					foreignKeyName="early_alert_reason_created_by_person_id"
					references="person(id)" />
			</column>
			<column name="modified_by" type="uuid">
				<constraints nullable="true"
					foreignKeyName="early_alert_reason_modified_by_person_id"
					references="person(id)" />
			</column>
			<column name="object_status" type="int">
				<constraints nullable="false" />
			</column>
			<column name="sort_order" type="smallint" defaultValue="0">
				<constraints nullable="false" />
			</column>
		</createTable>

		<sql>grant all on early_alert_reason to ssp</sql>
		<rollback>
			<dropTable tableName="early_alert_reason" />
		</rollback>

		<!-- Theres a different assumption in the liquibase handling of timezones 
			on postgres. Specifying "Without" timezone -->
		<modifySql dbms="postgresql">
			<replace replace="WITH TIME ZONE" with="WITHOUT TIME ZONE" />
		</modifySql>
	</changeSet>

	<changeSet id="create reference data - early_alert_reason"
		author="jon.adams">
		<insert tableName="early_alert_reason">
			<column name="id" value="1F5729AF-0337-4E58-A001-8A9F80DBF8AA" />
			<column name="name"
				value="Answered Yes to Critical Self Help Guide Question" />
			<column name="description"
				value="Answered Yes to Critical Self Help Guide Question" />
			<column name="created_date" valueDate="2012-05-03T00:00:00" />
			<column name="modified_date" valueDate="2012-05-03T00:00:00" />
			<column name="created_by" value="58ba5ee3-734e-4ae9-b9c5-943774b4de41" />
			<column name="modified_by" value="58ba5ee3-734e-4ae9-b9c5-943774b4de41" />
			<column name="object_status" value="1" />
			<column name="sort_order" value="9" />
		</insert>
		<insert tableName="early_alert_reason">
			<column name="id" value="300D68EF-38C2-4B7D-AD46-7874AA5D34AC" />
			<column name="name" value="Self Help Guide Threshold Exceeded" />
			<column name="description" value="Self Help Guide Threshold Exceeded" />
			<column name="created_date" valueDate="2012-05-03T00:00:00" />
			<column name="modified_date" valueDate="2012-05-03T00:00:00" />
			<column name="created_by" value="58ba5ee3-734e-4ae9-b9c5-943774b4de41" />
			<column name="modified_by" value="58ba5ee3-734e-4ae9-b9c5-943774b4de41" />
			<column name="object_status" value="1" />
			<column name="sort_order" value="10" />
		</insert>
		<insert tableName="early_alert_reason">
			<column name="id" value="B2D112A9-5056-A51A-8010B510525EA3A8" />
			<column name="name" value="Academic Concern" />
			<column name="description" value="Academic Concern" />
			<column name="created_date" valueDate="2012-05-03T00:00:00" />
			<column name="modified_date" valueDate="2012-05-03T00:00:00" />
			<column name="created_by" value="58ba5ee3-734e-4ae9-b9c5-943774b4de41" />
			<column name="modified_by" value="58ba5ee3-734e-4ae9-b9c5-943774b4de41" />
			<column name="object_status" value="1" />
			<column name="sort_order" value="1" />
		</insert>
		<insert tableName="early_alert_reason">
			<column name="id" value="B2D112B8-5056-A51A-80671FDA2849C3E5" />
			<column name="name" value="Excessive Absences" />
			<column name="description" value="Excessive Absences" />
			<column name="created_date" valueDate="2012-05-03T00:00:00" />
			<column name="modified_date" valueDate="2012-05-03T00:00:00" />
			<column name="created_by" value="58ba5ee3-734e-4ae9-b9c5-943774b4de41" />
			<column name="modified_by" value="58ba5ee3-734e-4ae9-b9c5-943774b4de41" />
			<column name="object_status" value="1" />
			<column name="sort_order" value="2" />
		</insert>
		<insert tableName="early_alert_reason">
			<column name="id" value="B2D112C8-5056-A51A-80D5BEEC7D48CB5D" />
			<column name="name" value="Low Homework/Quizzes" />
			<column name="description" value="Low Homework/Quizzes" />
			<column name="created_date" valueDate="2012-05-03T00:00:00" />
			<column name="modified_date" valueDate="2012-05-03T00:00:00" />
			<column name="created_by" value="58ba5ee3-734e-4ae9-b9c5-943774b4de41" />
			<column name="modified_by" value="58ba5ee3-734e-4ae9-b9c5-943774b4de41" />
			<column name="object_status" value="1" />
			<column name="sort_order" value="3" />
		</insert>
		<insert tableName="early_alert_reason">
			<column name="id" value="B2D112D7-5056-A51A-80AA795E56155AF5" />
			<column name="name" value="Low Test Scores" />
			<column name="description" value="Low Test Scores" />
			<column name="created_date" valueDate="2012-05-03T00:00:00" />
			<column name="modified_date" valueDate="2012-05-03T00:00:00" />
			<column name="created_by" value="58ba5ee3-734e-4ae9-b9c5-943774b4de41" />
			<column name="modified_by" value="58ba5ee3-734e-4ae9-b9c5-943774b4de41" />
			<column name="object_status" value="1" />
			<column name="sort_order" value="4" />
		</insert>
		<insert tableName="early_alert_reason">
			<column name="id" value="B2D112E7-5056-A51A-80E8A30645C463E4" />
			<column name="name" value="Never Attended" />
			<column name="description" value="Never Attended" />
			<column name="created_date" valueDate="2012-05-03T00:00:00" />
			<column name="modified_date" valueDate="2012-05-03T00:00:00" />
			<column name="created_by" value="58ba5ee3-734e-4ae9-b9c5-943774b4de41" />
			<column name="modified_by" value="58ba5ee3-734e-4ae9-b9c5-943774b4de41" />
			<column name="object_status" value="1" />
			<column name="sort_order" value="5" />
		</insert>
		<insert tableName="early_alert_reason">
			<column name="id" value="B2D11316-5056-A51A-80F979421BDF08BF" />
			<column name="name" value="Personal Concern" />
			<column name="description" value="Personal Concern" />
			<column name="created_date" valueDate="2012-05-03T00:00:00" />
			<column name="modified_date" valueDate="2012-05-03T00:00:00" />
			<column name="created_by" value="58ba5ee3-734e-4ae9-b9c5-943774b4de41" />
			<column name="modified_by" value="58ba5ee3-734e-4ae9-b9c5-943774b4de41" />
			<column name="object_status" value="1" />
			<column name="sort_order" value="6" />
		</insert>
		<insert tableName="early_alert_reason">
			<column name="id" value="B2D11326-5056-A51A-806C79F352D0C2B2" />
			<column name="name" value="Tardiness" />
			<column name="description" value="Tardiness" />
			<column name="created_date" valueDate="2012-05-03T00:00:00" />
			<column name="modified_date" valueDate="2012-05-03T00:00:00" />
			<column name="created_by" value="58ba5ee3-734e-4ae9-b9c5-943774b4de41" />
			<column name="modified_by" value="58ba5ee3-734e-4ae9-b9c5-943774b4de41" />
			<column name="object_status" value="1" />
			<column name="sort_order" value="7" />
		</insert>
		<insert tableName="early_alert_reason">
			<column name="id" value="B2D11335-5056-A51A-80EA074F8FEF94EA" />
			<column name="name" value="Other" />
			<column name="description" value="Other" />
			<column name="created_date" valueDate="2012-05-03T00:00:00" />
			<column name="modified_date" valueDate="2012-05-03T00:00:00" />
			<column name="created_by" value="58ba5ee3-734e-4ae9-b9c5-943774b4de41" />
			<column name="modified_by" value="58ba5ee3-734e-4ae9-b9c5-943774b4de41" />
			<column name="object_status" value="1" />
			<column name="sort_order" value="8" />
		</insert>
		<rollback>
			<delete tableName="early_alert_reason">
				<where>id='1F5729AF-0337-4E58-A001-8A9F80DBF8AA'</where>
			</delete>
			<delete tableName="early_alert_reason">
				<where>id='300D68EF-38C2-4B7D-AD46-7874AA5D34AC'</where>
			</delete>
			<delete tableName="early_alert_reason">
				<where>id='B2D112A9-5056-A51A-8010B510525EA3A8'</where>
			</delete>
			<delete tableName="early_alert_reason">
				<where>id='B2D112B8-5056-A51A-80671FDA2849C3E5'</where>
			</delete>
			<delete tableName="early_alert_reason">
				<where>id='B2D112C8-5056-A51A-80D5BEEC7D48CB5D'</where>
			</delete>
			<delete tableName="early_alert_reason">
				<where>id='B2D112D7-5056-A51A-80AA795E56155AF5'</where>
			</delete>
			<delete tableName="early_alert_reason">
				<where>id='B2D112E7-5056-A51A-80E8A30645C463E4'</where>
			</delete>
			<delete tableName="early_alert_reason">
				<where>id='B2D11316-5056-A51A-80F979421BDF08BF'</where>
			</delete>
			<delete tableName="early_alert_reason">
				<where>id='B2D11326-5056-A51A-806C79F352D0C2B2'</where>
			</delete>
			<delete tableName="early_alert_reason">
				<where>id='B2D11335-5056-A51A-80EA074F8FEF94EA'</where>
			</delete>
		</rollback>
	</changeSet>

	<changeSet author='jon.adams' id='Add early_alert_outreach table'>
		<createTable tableName="early_alert_outreach">
			<column name="id" type="uuid">
				<constraints primaryKey="true" nullable="false" />
			</column>
			<column name="name" type="character varying(80)">
				<constraints nullable="false" />
			</column>
			<column name="description" type="text">
				<constraints nullable="true" />
			</column>
			<column name="created_date" type="datetime">
				<constraints nullable="false" />
			</column>
			<column name="modified_date" type="datetime" />
			<column name="created_by" type="uuid">
				<constraints nullable="false"
					foreignKeyName="early_alert_outreach_created_by_person_id"
					references="person(id)" />
			</column>
			<column name="modified_by" type="uuid">
				<constraints nullable="true"
					foreignKeyName="early_alert_outreach_modified_by_person_id"
					references="person(id)" />
			</column>
			<column name="object_status" type="int">
				<constraints nullable="false" />
			</column>
			<column name="sort_order" type="smallint" defaultValue="0">
				<constraints nullable="false" />
			</column>
		</createTable>

		<sql>grant all on early_alert_outreach to ssp</sql>
		<rollback>
			<dropTable tableName="early_alert_outreach" />
		</rollback>

		<!-- Theres a different assumption in the liquibase handling of timezones 
			on postgres. Specifying "Without" timezone -->
		<modifySql dbms="postgresql">
			<replace replace="WITH TIME ZONE" with="WITHOUT TIME ZONE" />
		</modifySql>
	</changeSet>

	<changeSet id="create reference data - early_alert_outreach"
		author="jon.adams">
		<insert tableName="early_alert_outreach">
			<column name="id" value="9842EFF0-6557-4FB2-81C2-614991D5CBFB" />
			<column name="name" value="Phone Call" />
			<column name="description" value="Phone call" />
			<column name="created_date" valueDate="2012-05-04T00:00:00" />
			<column name="modified_date" valueDate="2012-05-04T15:00:00" />
			<column name="created_by" value="58ba5ee3-734e-4ae9-b9c5-943774b4de41" />
			<column name="modified_by" value="58ba5ee3-734e-4ae9-b9c5-943774b4de41" />
			<column name="object_status" value="1" />
			<column name="sort_order" value="5" />
		</insert>
		<insert tableName="early_alert_outreach">
			<column name="id" value="3383D46F-8051-4A86-886D-A3EFE75B8F3A" />
			<column name="name" value="Email" />
			<column name="description" value="Email" />
			<column name="created_date" valueDate="2012-05-04T15:00:00" />
			<column name="modified_date" valueDate="2012-05-04T15:00:00" />
			<column name="created_by" value="58ba5ee3-734e-4ae9-b9c5-943774b4de41" />
			<column name="modified_by" value="58ba5ee3-734e-4ae9-b9c5-943774b4de41" />
			<column name="object_status" value="1" />
			<column name="sort_order" value="10" />
		</insert>
		<insert tableName="early_alert_outreach">
			<column name="id" value="BA387302-B08B-4DC2-BD3F-AEFC2FC8D092" />
			<column name="name" value="Letter" />
			<column name="description" value="Letter" />
			<column name="created_date" valueDate="2012-05-04T15:00:00" />
			<column name="modified_date" valueDate="2012-05-04T15:00:00" />
			<column name="created_by" value="58ba5ee3-734e-4ae9-b9c5-943774b4de41" />
			<column name="modified_by" value="58ba5ee3-734e-4ae9-b9c5-943774b4de41" />
			<column name="object_status" value="1" />
			<column name="sort_order" value="15" />
		</insert>
		<insert tableName="early_alert_outreach">
			<column name="id" value="E7908476-E67D-4FB2-890B-2D4E6C9B0E42" />
			<column name="name" value="Text" />
			<column name="description" value="Text" />
			<column name="created_date" valueDate="2012-05-04T15:00:00" />
			<column name="modified_date" valueDate="2012-05-04T15:00:00" />
			<column name="created_by" value="58ba5ee3-734e-4ae9-b9c5-943774b4de41" />
			<column name="modified_by" value="58ba5ee3-734e-4ae9-b9c5-943774b4de41" />
			<column name="object_status" value="1" />
			<column name="sort_order" value="20" />
		</insert>
		<insert tableName="early_alert_outreach">
			<column name="id" value="612ED2C5-6D9A-4CDA-9007-B22756888CA8" />
			<column name="name" value="In Person" />
			<column name="description" value="In person" />
			<column name="created_date" valueDate="2012-05-04T15:00:00" />
			<column name="modified_date" valueDate="2012-05-04T15:00:00" />
			<column name="created_by" value="58ba5ee3-734e-4ae9-b9c5-943774b4de41" />
			<column name="modified_by" value="58ba5ee3-734e-4ae9-b9c5-943774b4de41" />
			<column name="object_status" value="1" />
			<column name="sort_order" value="25" />
		</insert>
		<rollback>
			<delete tableName="early_alert_outreach">
				<where>id='9842EFF0-6557-4FB2-81C2-614991D5CBFB'</where>
			</delete>
			<delete tableName="early_alert_outreach">
				<where>id='3383D46F-8051-4A86-886D-A3EFE75B8F3A'</where>
			</delete>
			<delete tableName="early_alert_outreach">
				<where>id='BA387302-B08B-4DC2-BD3F-AEFC2FC8D092'</where>
			</delete>
			<delete tableName="early_alert_outreach">
				<where>id='E7908476-E67D-4FB2-890B-2D4E6C9B0E42'</where>
			</delete>
			<delete tableName="early_alert_outreach">
				<where>id='612ED2C5-6D9A-4CDA-9007-B22756888CA8'</where>
			</delete>
		</rollback>
	</changeSet>

	<changeSet author='jon.adams' id='Add early_alert_outcome table'>
		<createTable tableName="early_alert_outcome">
			<column name="id" type="uuid">
				<constraints primaryKey="true" nullable="false" />
			</column>
			<column name="name" type="character varying(80)">
				<constraints nullable="false" />
			</column>
			<column name="description" type="text">
				<constraints nullable="true" />
			</column>
			<column name="created_date" type="datetime">
				<constraints nullable="false" />
			</column>
			<column name="modified_date" type="datetime" />
			<column name="created_by" type="uuid">
				<constraints nullable="false"
					foreignKeyName="early_alert_outcome_created_by_person_id"
					references="person(id)" />
			</column>
			<column name="modified_by" type="uuid">
				<constraints nullable="true"
					foreignKeyName="early_alert_outcome_modified_by_person_id"
					references="person(id)" />
			</column>
			<column name="object_status" type="int">
				<constraints nullable="false" />
			</column>
			<column name="sort_order" type="smallint" defaultValue="0">
				<constraints nullable="false" />
			</column>
		</createTable>

		<sql>grant all on early_alert_outcome to ssp</sql>
		<rollback>
			<dropTable tableName="early_alert_outcome" />
		</rollback>

		<!-- Theres a different assumption in the liquibase handling of timezones 
			on postgres. Specifying "Without" timezone -->
		<modifySql dbms="postgresql">
			<replace replace="WITH TIME ZONE" with="WITHOUT TIME ZONE" />
		</modifySql>
	</changeSet>

	<changeSet id="create reference data - early_alert_outcome"
		author="jon.adams">
		<insert tableName="early_alert_outcome">
			<column name="id" value="B2D10FCA-5056-A51A-80888103AC163F13" />
			<column name="name" value="Appointment Scheduled" />
			<column name="description" value="AS" />
			<column name="created_date" valueDate="2012-05-03T00:00:00" />
			<column name="modified_date" valueDate="2012-05-03T00:00:00" />
			<column name="created_by" value="58ba5ee3-734e-4ae9-b9c5-943774b4de41" />
			<column name="modified_by" value="58ba5ee3-734e-4ae9-b9c5-943774b4de41" />
			<column name="object_status" value="1" />
			<column name="sort_order" value="1" />
		</insert>
		<insert tableName="early_alert_outcome">
			<column name="id" value="B2D10FE9-5056-A51A-80456B36326A6463" />
			<column name="name"
				value="Assistance Declined: Declines all or any assistance" />
			<column name="description" value="ASD" />
			<column name="created_date" valueDate="2012-05-03T00:00:00" />
			<column name="modified_date" valueDate="2012-05-03T00:00:00" />
			<column name="created_by" value="58ba5ee3-734e-4ae9-b9c5-943774b4de41" />
			<column name="modified_by" value="58ba5ee3-734e-4ae9-b9c5-943774b4de41" />
			<column name="object_status" value="1" />
			<column name="sort_order" value="2" />
		</insert>
		<insert tableName="early_alert_outcome">
			<column name="id" value="B2D10FF9-5056-A51A-80BEED3F1F11C9A9" />
			<column name="name"
				value="Considering Future Services: May attend workshops" />
			<column name="description" value="CFS" />
			<column name="created_date" valueDate="2012-05-03T00:00:00" />
			<column name="modified_date" valueDate="2012-05-03T00:00:00" />
			<column name="created_by" value="58ba5ee3-734e-4ae9-b9c5-943774b4de41" />
			<column name="modified_by" value="58ba5ee3-734e-4ae9-b9c5-943774b4de41" />
			<column name="object_status" value="1" />
			<column name="sort_order" value="3" />
		</insert>
		<insert tableName="early_alert_outcome">
			<column name="id" value="B2D11009-5056-A51A-8072ED4EBFA88DA5" />
			<column name="name" value="Letter Sent" />
			<column name="description" value="LS" />
			<column name="created_date" valueDate="2012-05-03T00:00:00" />
			<column name="modified_date" valueDate="2012-05-03T00:00:00" />
			<column name="created_by" value="58ba5ee3-734e-4ae9-b9c5-943774b4de41" />
			<column name="modified_by" value="58ba5ee3-734e-4ae9-b9c5-943774b4de41" />
			<column name="object_status" value="1" />
			<column name="sort_order" value="4" />
		</insert>
		<insert tableName="early_alert_outcome">
			<column name="id" value="B2D11018-5056-A51A-801FBEF6DC4AC7EF" />
			<column name="name" value="Not Attending Sinclair Community College" />
			<column name="description" value="NAS" />
			<column name="created_date" valueDate="2012-05-03T00:00:00" />
			<column name="modified_date" valueDate="2012-05-03T00:00:00" />
			<column name="created_by" value="58ba5ee3-734e-4ae9-b9c5-943774b4de41" />
			<column name="modified_by" value="58ba5ee3-734e-4ae9-b9c5-943774b4de41" />
			<column name="object_status" value="1" />
			<column name="sort_order" value="5" />
		</insert>
		<insert tableName="early_alert_outcome">
			<column name="id" value="B2D11028-5056-A51A-80E9E86DEA9498D8" />
			<column name="name"
				value="No Response to Letter Sent or Phone or Email Messages" />
			<column name="description" value="NR" />
			<column name="created_date" valueDate="2012-05-03T00:00:00" />
			<column name="modified_date" valueDate="2012-05-03T00:00:00" />
			<column name="created_by" value="58ba5ee3-734e-4ae9-b9c5-943774b4de41" />
			<column name="modified_by" value="58ba5ee3-734e-4ae9-b9c5-943774b4de41" />
			<column name="object_status" value="1" />
			<column name="sort_order" value="6" />
		</insert>
		<insert tableName="early_alert_outcome">
			<column name="id" value="B2D11076-5056-A51A-80C1F5813762FF0B" />
			<column name="name" value="Other" />
			<column name="description" value="OTH" />
			<column name="created_date" valueDate="2012-05-03T00:00:00" />
			<column name="modified_date" valueDate="2012-05-03T00:00:00" />
			<column name="created_by" value="58ba5ee3-734e-4ae9-b9c5-943774b4de41" />
			<column name="modified_by" value="58ba5ee3-734e-4ae9-b9c5-943774b4de41" />
			<column name="object_status" value="1" />
			<column name="sort_order" value="7" />
		</insert>
		<insert tableName="early_alert_outcome">
			<column name="id" value="B2D11086-5056-A51A-8034893608D7A6C7" />
			<column name="name" value="Problem Addressed" />
			<column name="description" value="PA" />
			<column name="created_date" valueDate="2012-05-03T00:00:00" />
			<column name="modified_date" valueDate="2012-05-03T00:00:00" />
			<column name="created_by" value="58ba5ee3-734e-4ae9-b9c5-943774b4de41" />
			<column name="modified_by" value="58ba5ee3-734e-4ae9-b9c5-943774b4de41" />
			<column name="object_status" value="1" />
			<column name="sort_order" value="8" />
		</insert>
		<insert tableName="early_alert_outcome">
			<column name="id" value="B2D11095-5056-A51A-80A8F6F9B7975595" />
			<column name="name"
				value="Problem Addressed by Referral to Sinclair Department" />
			<column name="description" value="PARSD" />
			<column name="created_date" valueDate="2012-05-03T00:00:00" />
			<column name="modified_date" valueDate="2012-05-03T00:00:00" />
			<column name="created_by" value="58ba5ee3-734e-4ae9-b9c5-943774b4de41" />
			<column name="modified_by" value="58ba5ee3-734e-4ae9-b9c5-943774b4de41" />
			<column name="object_status" value="1" />
			<column name="sort_order" value="9" />
		</insert>
		<insert tableName="early_alert_outcome">
			<column name="id" value="B2D110A5-5056-A51A-808BF40B80601A46" />
			<column name="name" value="Unable to Reach: Disconnect busy number changed" />
			<column name="description" value="UTR" />
			<column name="created_date" valueDate="2012-05-03T00:00:00" />
			<column name="modified_date" valueDate="2012-05-03T00:00:00" />
			<column name="created_by" value="58ba5ee3-734e-4ae9-b9c5-943774b4de41" />
			<column name="modified_by" value="58ba5ee3-734e-4ae9-b9c5-943774b4de41" />
			<column name="object_status" value="1" />
			<column name="sort_order" value="10" />
		</insert>
		<insert tableName="early_alert_outcome">
			<column name="id" value="B2D110B4-5056-A51A-809B35E8C9C4DE86" />
			<column name="name" value="Pending" />
			<column name="description" value="P" />
			<column name="created_date" valueDate="2012-05-03T00:00:00" />
			<column name="modified_date" valueDate="2012-05-03T00:00:00" />
			<column name="created_by" value="58ba5ee3-734e-4ae9-b9c5-943774b4de41" />
			<column name="modified_by" value="58ba5ee3-734e-4ae9-b9c5-943774b4de41" />
			<column name="object_status" value="1" />
			<column name="sort_order" value="11" />
		</insert>
		<rollback>
			<delete tableName="early_alert_outcome">
				<where>id='B2D10FCA-5056-A51A-80888103AC163F13'</where>
			</delete>
			<delete tableName="early_alert_outcome">
				<where>id='B2D10FE9-5056-A51A-80456B36326A6463'</where>
			</delete>
			<delete tableName="early_alert_outcome">
				<where>id='B2D10FF9-5056-A51A-80BEED3F1F11C9A9'</where>
			</delete>
			<delete tableName="early_alert_outcome">
				<where>id='B2D11009-5056-A51A-8072ED4EBFA88DA5'</where>
			</delete>
			<delete tableName="early_alert_outcome">
				<where>id='B2D11018-5056-A51A-801FBEF6DC4AC7EF'</where>
			</delete>
			<delete tableName="early_alert_outcome">
				<where>id='B2D11028-5056-A51A-80E9E86DEA9498D8'</where>
			</delete>
			<delete tableName="early_alert_outcome">
				<where>id='B2D11076-5056-A51A-80C1F5813762FF0B'</where>
			</delete>
			<delete tableName="early_alert_outcome">
				<where>id='B2D11086-5056-A51A-8034893608D7A6C7'</where>
			</delete>
			<delete tableName="early_alert_outcome">
				<where>id='B2D11095-5056-A51A-80A8F6F9B7975595'</where>
			</delete>
			<delete tableName="early_alert_outcome">
				<where>id='B2D110A5-5056-A51A-808BF40B80601A46'</where>
			</delete>
			<delete tableName="early_alert_outcome">
				<where>id='B2D110B4-5056-A51A-809B35E8C9C4DE86'</where>
			</delete>
		</rollback>
	</changeSet>

	<changeSet author='jon.adams' id='Add early_alert table'>
		<createTable tableName="early_alert">
			<column name="id" type="uuid">
				<constraints primaryKey="true" nullable="false" />
			</column>
			<column name="created_date" type="datetime">
				<constraints nullable="false" />
			</column>
			<column name="modified_date" type="datetime" />
			<column name="created_by" type="uuid">
				<constraints nullable="false"
					foreignKeyName="early_alert_suggestion_created_by_person_id"
					references="person(id)" />
			</column>
			<column name="modified_by" type="uuid">
				<constraints nullable="true"
					foreignKeyName="early_alert_suggestion_modified_by_person_id"
					references="person(id)" />
			</column>
			<column name="object_status" type="int">
				<constraints nullable="false" />
			</column>
			<column name="course_name" type="character varying(80)">
				<constraints nullable="true" />
			</column>
			<column name="course_title" type="character varying(255)">
				<constraints nullable="true" />
			</column>
			<column name="email_cc" type="character varying(255)">
				<constraints nullable="true" />
			</column>
			<column name="person_id" type="uuid">
				<constraints nullable="false" foreignKeyName="early_alert_person_id"
					references="person(id)" />
			</column>
			<column name="campus_id" type="int">
				<constraints nullable="true" />
			</column>
			<column name="early_alert_reason_other_description" type="text">
				<constraints nullable="true" />
			</column>
			<column name="comment" type="text">
				<constraints nullable="true" />
			</column>
		</createTable>

		<sql>grant all on early_alert to ssp</sql>
		<rollback>
			<dropTable tableName="early_alert" />
		</rollback>

		<!-- Theres a different assumption in the liquibase handling of timezones 
			on postgres. Specifying "Without" timezone -->
		<modifySql dbms="postgresql">
			<replace replace="WITH TIME ZONE" with="WITHOUT TIME ZONE" />
		</modifySql>
	</changeSet>

	<changeSet author='jon.adams' id='Add early_alert_early_alert_reason table'>
		<createTable tableName="early_alert_early_alert_reason">
			<column name="id" type="uuid">
				<constraints primaryKey="true" nullable="false" />
			</column>
			<column name="created_date" type="datetime">
				<constraints nullable="false" />
			</column>
			<column name="modified_date" type="datetime" />
			<column name="created_by" type="uuid">
				<constraints nullable="false"
					foreignKeyName="early_alert_suggestion_created_by_person_id"
					references="person(id)" />
			</column>
			<column name="modified_by" type="uuid">
				<constraints nullable="true"
					foreignKeyName="early_alert_suggestion_modified_by_person_id"
					references="person(id)" />
			</column>
			<column name="object_status" type="int">
				<constraints nullable="false" />
			</column>
			<column name="early_alert_id" type="uuid">
				<constraints nullable="false"
					foreignKeyName="early_alert_reason_early_alert_id" references="early_alert(id)" />
			</column>
			<column name="early_alert_reason_id" type="uuid">
				<constraints nullable="false"
					foreignKeyName="early_alert_reason_early_alert_reason_id"
					references="early_alert_reason(id)" />
			</column>
		</createTable>

		<sql>grant all on early_alert_early_alert_reason to ssp</sql>
		<rollback>
			<dropTable tableName="early_alert_early_alert_reason" />
		</rollback>

		<!-- Theres a different assumption in the liquibase handling of timezones 
			on postgres. Specifying "Without" timezone -->
		<modifySql dbms="postgresql">
			<replace replace="WITH TIME ZONE" with="WITHOUT TIME ZONE" />
		</modifySql>
	</changeSet>

	<changeSet author='jon.adams'
		id='Add early_alert_early_alert_suggestion table'>
		<createTable tableName="early_alert_early_alert_suggestion">
			<column name="id" type="uuid">
				<constraints primaryKey="true" nullable="false" />
			</column>
			<column name="created_date" type="datetime">
				<constraints nullable="false" />
			</column>
			<column name="modified_date" type="datetime" />
			<column name="created_by" type="uuid">
				<constraints nullable="false"
					foreignKeyName="early_alert_suggestion_created_by_person_id"
					references="person(id)" />
			</column>
			<column name="modified_by" type="uuid">
				<constraints nullable="true"
					foreignKeyName="early_alert_suggestion_modified_by_person_id"
					references="person(id)" />
			</column>
			<column name="object_status" type="int">
				<constraints nullable="false" />
			</column>
			<column name="early_alert_id" type="uuid">
				<constraints nullable="false"
					foreignKeyName="early_alert_suggestion_early_alert_id" references="early_alert(id)" />
			</column>
			<column name="early_alert_suggestion_id" type="uuid">
				<constraints nullable="false"
					foreignKeyName="early_alert_suggestion_early_alert_suggestion_id"
					references="early_alert_suggestion(id)" />
			</column>
		</createTable>

		<sql>grant all on early_alert_early_alert_suggestion to ssp</sql>
		<rollback>
			<dropTable tableName="early_alert_early_alert_suggestion" />
		</rollback>

		<!-- Theres a different assumption in the liquibase handling of timezones 
			on postgres. Specifying "Without" timezone -->
		<modifySql dbms="postgresql">
			<replace replace="WITH TIME ZONE" with="WITHOUT TIME ZONE" />
		</modifySql>
	</changeSet>

	<changeSet id="sample deleted data for testing early_alert_outcome"
		author="jon.adams">
		<insert tableName="early_alert_outcome">
			<column name="id" value="077A1D57-6C85-42F7-922B-7642BE9F70EB" />
			<column name="name" value="Test deleted outcome - should never be seen" />
			<column name="description" value="TEST" />
			<column name="created_date" valueDate="2012-05-07T11:00:00" />
			<column name="modified_date" valueDate="2012-05-07T11:00:00" />
			<column name="created_by" value="58ba5ee3-734e-4ae9-b9c5-943774b4de41" />
			<column name="modified_by" value="58ba5ee3-734e-4ae9-b9c5-943774b4de41" />
			<column name="object_status" value="3" />
			<column name="sort_order" value="100" />
		</insert>
		<rollback>
			<delete tableName="early_alert_outcome">
				<where>id='077A1D57-6C85-42F7-922B-7642BE9F70EB'</where>
			</delete>
		</rollback>
	</changeSet>

	<changeSet id="sample deleted data for testing early_alert_suggestion"
		author="jon.adams">
		<insert tableName="early_alert_suggestion">
			<column name="id" value="881DF3DD-1AA6-4CB8-8817-E95DAF49227A" />
			<column name="name" value="Test deleted suggestion - should never be seen" />
			<column name="description" value="TEST" />
			<column name="created_date" valueDate="2012-05-07T12:00:00" />
			<column name="modified_date" valueDate="2012-05-07T12:00:00" />
			<column name="created_by" value="58ba5ee3-734e-4ae9-b9c5-943774b4de41" />
			<column name="modified_by" value="58ba5ee3-734e-4ae9-b9c5-943774b4de41" />
			<column name="object_status" value="3" />
			<column name="sort_order" value="100" />
		</insert>
		<rollback>
			<delete tableName="early_alert_suggestion">
				<where>id='881DF3DD-1AA6-4CB8-8817-E95DAF49227A'</where>
			</delete>
		</rollback>
	</changeSet>

	<changeSet author='jon.adams'
		id='Change early_alert_early_alert_reason table'>
		<dropTable tableName="early_alert_early_alert_reason" />
		<createTable tableName="early_alert_early_alert_reason">
			<column name="early_alert_id" type="uuid">
				<constraints nullable="false"
					foreignKeyName="early_alert_early_alert_reason_early_alert_id"
					references="early_alert(id)" primaryKey="true" />
			</column>
			<column name="early_alert_reason_id" type="uuid">
				<constraints nullable="false"
					foreignKeyName="early_alert_early_alert_reason_ids" references="early_alert_reason(id)"
					primaryKey="true" />
			</column>
		</createTable>

		<sql>grant all on early_alert_early_alert_reason to ssp</sql>
		<rollback>
			<dropTable tableName="early_alert_early_alert_reason" />
		</rollback>

		<!-- Theres a different assumption in the liquibase handling of timezones 
			on postgres. Specifying "Without" timezone -->
		<modifySql dbms="postgresql">
			<replace replace="WITH TIME ZONE" with="WITHOUT TIME ZONE" />
		</modifySql>
	</changeSet>

	<changeSet author='jon.adams'
		id='Change early_alert_early_alert_suggestion table'>
		<dropTable tableName="early_alert_early_alert_suggestion" />
		<createTable tableName="early_alert_early_alert_suggestion">
			<column name="early_alert_id" type="uuid">
				<constraints nullable="false"
					foreignKeyName="early_alert_early_alert_suggestion_early_alert_id"
					references="early_alert(id)" primaryKey="true" />
			</column>
			<column name="early_alert_suggestion_id" type="uuid">
				<constraints nullable="false"
					foreignKeyName="early_alert_early_alert_suggestion_ids" references="early_alert_suggestion(id)"
					primaryKey="true" />
			</column>
		</createTable>

		<sql>grant all on early_alert_early_alert_suggestion to ssp</sql>
		<rollback>
			<dropTable tableName="early_alert_early_alert_suggestion" />
		</rollback>

		<!-- Theres a different assumption in the liquibase handling of timezones 
			on postgres. Specifying "Without" timezone -->
		<modifySql dbms="postgresql">
			<replace replace="WITH TIME ZONE" with="WITHOUT TIME ZONE" />
		</modifySql>
	</changeSet>

	<changeSet id="Add Journal Entry table" author="daniel.bower">
		<createTable tableName="journal_entry">
			<column name="id" type="uuid">
				<constraints primaryKey="true" nullable="false" />
			</column>
			<column name="created_date" type="datetime">
				<constraints nullable="false" />
			</column>
			<column name="modified_date" type="datetime">
				<constraints nullable="false" />
			</column>
			<column name="created_by" type="uuid">
				<constraints nullable="false"
					foreignKeyName="journal_entry_created_by_person_id" references="person(id)" />
			</column>
			<column name="modified_by" type="uuid">
				<constraints nullable="false"
					foreignKeyName="journal_entry_modified_by_person_id" references="person(id)" />
			</column>
			<column name="object_status" type="int">
				<constraints nullable="false" />
			</column>
			<column name="entry_date" type="datetime">
				<constraints nullable="false" />
			</column>
			<column name="comment" type="text">
				<constraints nullable="true" />
			</column>
			<column name="confidentiality_level_id" type="uuid">
				<constraints nullable="false"
					foreignKeyName="journal_entry_confidentiality_level_id_person_id"
					references="confidentiality_level(id)" />
			</column>
			<column name="journal_source_id" type="uuid">
				<constraints nullable="false"
					foreignKeyName="journal_entry_journal_source_id_person_id"
					references="journal_source(id)" />
			</column>
			<column name="journal_track_id" type="uuid">
				<constraints nullable="false"
					foreignKeyName="journal_entry_journal_track_id_person_id"
					references="journal_track(id)" />
			</column>
			<column name="person_id" type="uuid">
				<constraints nullable="false"
					foreignKeyName="journal_entry_person_id_person_id" references="person(id)" />
			</column>
		</createTable>

		<sql>grant all on journal_entry to ssp</sql>
		<rollback>
			<dropTable tableName="journal_entry" />
		</rollback>

		<!-- Theres a different assumption in the liquibase handling of timezones 
			on postgres. Specifying "Without" timezone -->
		<modifySql dbms="postgresql">
			<replace replace="WITH TIME ZONE" with="WITHOUT TIME ZONE" />
		</modifySql>
	</changeSet>

	<changeSet id="Add JournalEntryJournalStepDetail table"
		author="daniel.bower">
		<createTable tableName="journal_entry_journal_step_detail">
			<column name="id" type="uuid">
				<constraints primaryKey="true" nullable="false" />
			</column>
			<column name="created_date" type="datetime">
				<constraints nullable="false" />
			</column>
			<column name="modified_date" type="datetime">
				<constraints nullable="false" />
			</column>
			<column name="created_by" type="uuid">
				<constraints nullable="false"
					foreignKeyName="journal_entry_journal_step_detail_created_by_person_id"
					references="person(id)" />
			</column>
			<column name="modified_by" type="uuid">
				<constraints nullable="false"
					foreignKeyName="journal_entry_journal_step_detail_modified_by_person_id"
					references="person(id)" />
			</column>
			<column name="object_status" type="int">
				<constraints nullable="false" />
			</column>
			<column name="journal_entry_id" type="uuid">
				<constraints nullable="false"
					foreignKeyName="journal_entry_journal_step_detail_journal_entry_id_journal_entry_id"
					references="journal_entry(id)" />
			</column>
			<column name="journal_step_detail_id" type="uuid">
				<constraints nullable="false"
					foreignKeyName="journal_entry_journal_step_detail_journal_step_detail_id_journal_step_detail_id"
					references="journal_step_detail(id)" />
			</column>
		</createTable>

		<sql>grant all on journal_entry_journal_step_detail to ssp</sql>
		<rollback>
			<dropTable tableName="journal_entry_journal_step_detail" />
		</rollback>

		<!-- Theres a different assumption in the liquibase handling of timezones 
			on postgres. Specifying "Without" timezone -->
		<modifySql dbms="postgresql">
			<replace replace="WITH TIME ZONE" with="WITHOUT TIME ZONE" />
		</modifySql>
	</changeSet>

	<changeSet author='jon.adams' id='Add campus table'>
		<createTable tableName="campus">
			<column name="id" type="uuid">
				<constraints primaryKey="true" nullable="false" />
			</column>
			<column name="name" type="character varying(80)">
				<constraints nullable="false" />
			</column>
			<column name="description" type="text">
				<constraints nullable="true" />
			</column>
			<column name="created_date" type="datetime">
				<constraints nullable="false" />
			</column>
			<column name="modified_date" type="datetime" />
			<column name="created_by" type="uuid">
				<constraints nullable="false"
					foreignKeyName="early_alert_suggestion_created_by_person_id"
					references="person(id)" />
			</column>
			<column name="modified_by" type="uuid">
				<constraints nullable="true"
					foreignKeyName="early_alert_suggestion_modified_by_person_id"
					references="person(id)" />
			</column>
			<column name="object_status" type="int">
				<constraints nullable="false" />
			</column>
			<column name="early_alert_coordinator_id" type="uuid">
				<constraints nullable="false" />
			</column>
		</createTable>

		<sql>grant all on campus to ssp</sql>
		<rollback>
			<dropTable tableName="campus" />
		</rollback>

		<!-- Theres a different assumption in the liquibase handling of timezones 
			on postgres. Specifying "Without" timezone -->
		<modifySql dbms="postgresql">
			<replace replace="WITH TIME ZONE" with="WITHOUT TIME ZONE" />
		</modifySql>
	</changeSet>

	<changeSet id="Add close to EarlyAlert" author="jon.adams">
		<addColumn tableName="early_alert">
			<column name="closed_date" type="datetime" />
			<column name="closed_by_id" type="uuid">
				<constraints nullable="true" foreignKeyName="early_alert_closed_by_person_id"
					references="person(id)" />
			</column>
		</addColumn>
		<rollback>
			<dropColumn tableName="early_alert" columnName="closed_date" />
			<dropColumn tableName="early_alert" columnName="closed_by_id" />
		</rollback>
	</changeSet>

	<changeSet author='jon.adams' id='Add early_alert_response table'>
		<createTable tableName="early_alert_response">
			<column name="id" type="uuid">
				<constraints primaryKey="true" nullable="false" />
			</column>
			<column name="created_date" type="datetime">
				<constraints nullable="false" />
			</column>
			<column name="modified_date" type="datetime" />
			<column name="created_by" type="uuid">
				<constraints nullable="false"
					foreignKeyName="early_alert_suggestion_created_by_person_id"
					references="person(id)" />
			</column>
			<column name="modified_by" type="uuid">
				<constraints nullable="true"
					foreignKeyName="early_alert_suggestion_modified_by_person_id"
					references="person(id)" />
			</column>
			<column name="object_status" type="int">
				<constraints nullable="false" />
			</column>
			<column name="early_alert_id" type="uuid">
				<constraints nullable="false"
					foreignKeyName="early_alert_response_early_alert_id" references="early_alert(id)" />
			</column>
			<column name="early_alert_outcome_id" type="uuid">
				<constraints nullable="false"
					foreignKeyName="early_alert_response_early_alert_outcome_id"
					references="early_alert_outcome(id)" />
			</column>
			<column name="early_alert_outcome_other_description" type="text">
				<constraints nullable="true" />
			</column>
			<column name="comment" type="text">
				<constraints nullable="true" />
			</column>
		</createTable>

		<sql>grant all on early_alert_response to ssp</sql>
		<rollback>
			<dropTable tableName="early_alert_response" />
		</rollback>

		<!-- Theres a different assumption in the liquibase handling of timezones 
			on postgres. Specifying "Without" timezone -->
		<modifySql dbms="postgresql">
			<replace replace="WITH TIME ZONE" with="WITHOUT TIME ZONE" />
		</modifySql>
	</changeSet>

	<changeSet author='jon.adams'
		id='Add early_alert_response_early_alert_outreach table'>
		<createTable tableName="early_alert_response_early_alert_outreach">
			<column name="early_alert_response_id" type="uuid">
				<constraints nullable="false"
					foreignKeyName="ea_response_ea_outreach_ea_response_id" references="early_alert_response(id)"
					primaryKey="true" />
			</column>
			<column name="early_alert_outreach_id" type="uuid">
				<constraints nullable="false"
					foreignKeyName="ea_response_ea_outreach_ea_outreach_id" references="early_alert_outreach(id)"
					primaryKey="true" />
			</column>
		</createTable>

		<sql>grant all on early_alert_response_early_alert_outreach to ssp
		</sql>
		<rollback>
			<dropTable tableName="early_alert_response_early_alert_outreach" />
		</rollback>

		<!-- Theres a different assumption in the liquibase handling of timezones 
			on postgres. Specifying "Without" timezone -->
		<modifySql dbms="postgresql">
			<replace replace="WITH TIME ZONE" with="WITHOUT TIME ZONE" />
		</modifySql>
	</changeSet>

	<changeSet author='jon.adams'
		id='Add early_alert_response_early_alert_referral table'>
		<createTable tableName="early_alert_response_early_alert_referral">
			<column name="early_alert_response_id" type="uuid">
				<constraints nullable="false"
					foreignKeyName="ea_response_ea_referral_ea_response_id" references="early_alert_response(id)"
					primaryKey="true" />
			</column>
			<column name="early_alert_referral_id" type="uuid">
				<constraints nullable="false"
					foreignKeyName="ea_response_ea_referral_ea_referral_id" references="early_alert_referral(id)"
					primaryKey="true" />
			</column>
		</createTable>

		<sql>grant all on early_alert_response_early_alert_referral to ssp
		</sql>
		<rollback>
			<dropTable tableName="early_alert_response_early_alert_referral" />
		</rollback>

		<!-- Theres a different assumption in the liquibase handling of timezones 
			on postgres. Specifying "Without" timezone -->
		<modifySql dbms="postgresql">
			<replace replace="WITH TIME ZONE" with="WITHOUT TIME ZONE" />
		</modifySql>
	</changeSet>

	<changeSet id="clean up early_alert_outcome sample data"
		author="jon.adams">
		<delete tableName="early_alert_outcome">
			<where>id='B2D10FCA-5056-A51A-80888103AC163F13'</where>
		</delete>
		<delete tableName="early_alert_outcome">
			<where>id='B2D10FE9-5056-A51A-80456B36326A6463'</where>
		</delete>
		<delete tableName="early_alert_outcome">
			<where>id='B2D10FF9-5056-A51A-80BEED3F1F11C9A9'</where>
		</delete>
		<delete tableName="early_alert_outcome">
			<where>id='B2D11009-5056-A51A-8072ED4EBFA88DA5'</where>
		</delete>
		<delete tableName="early_alert_outcome">
			<where>id='B2D11018-5056-A51A-801FBEF6DC4AC7EF'</where>
		</delete>
		<delete tableName="early_alert_outcome">
			<where>id='B2D11028-5056-A51A-80E9E86DEA9498D8'</where>
		</delete>
		<delete tableName="early_alert_outcome">
			<where>id='B2D11076-5056-A51A-80C1F5813762FF0B'</where>
		</delete>
		<delete tableName="early_alert_outcome">
			<where>id='B2D11086-5056-A51A-8034893608D7A6C7'</where>
		</delete>
		<delete tableName="early_alert_outcome">
			<where>id='B2D11095-5056-A51A-80A8F6F9B7975595'</where>
		</delete>
		<delete tableName="early_alert_outcome">
			<where>id='B2D110A5-5056-A51A-808BF40B80601A46'</where>
		</delete>
		<delete tableName="early_alert_outcome">
			<where>id='B2D110B4-5056-A51A-809B35E8C9C4DE86'</where>
		</delete>
		<insert tableName="early_alert_outcome">
			<column name="id" value="12A58804-45DC-40F2-B2F5-D7E4403ACEE1" />
			<column name="name" value="Student Responded" />
			<column name="description" value="Student responded" />
			<column name="created_date" valueDate="2012-05-11T10:00:00" />
			<column name="modified_date" valueDate="2012-05-11T10:00:00" />
			<column name="created_by" value="58ba5ee3-734e-4ae9-b9c5-943774b4de41" />
			<column name="modified_by" value="58ba5ee3-734e-4ae9-b9c5-943774b4de41" />
			<column name="object_status" value="1" />
			<column name="sort_order" value="1" />
		</insert>
		<insert tableName="early_alert_outcome">
			<column name="id" value="9A98FF78-92AF-4681-8111-ADB3300CBE1C" />
			<column name="name" value="Student Did Not Responsd" />
			<column name="description" value="Student did not responsd" />
			<column name="created_date" valueDate="2012-05-11T10:00:00" />
			<column name="modified_date" valueDate="2012-05-11T10:00:00" />
			<column name="created_by" value="58ba5ee3-734e-4ae9-b9c5-943774b4de41" />
			<column name="modified_by" value="58ba5ee3-734e-4ae9-b9c5-943774b4de41" />
			<column name="object_status" value="1" />
			<column name="sort_order" value="2" />
		</insert>
		<insert tableName="early_alert_outcome">
			<column name="id" value="7148606F-9034-4538-8FC2-C852A5C912EE" />
			<column name="name" value="Waiting for Response" />
			<column name="description" value="Waiting for response" />
			<column name="created_date" valueDate="2012-05-11T10:00:00" />
			<column name="modified_date" valueDate="2012-05-11T10:00:00" />
			<column name="created_by" value="58ba5ee3-734e-4ae9-b9c5-943774b4de41" />
			<column name="modified_by" value="58ba5ee3-734e-4ae9-b9c5-943774b4de41" />
			<column name="object_status" value="1" />
			<column name="sort_order" value="3" />
		</insert>
		<insert tableName="early_alert_outcome">
			<column name="id" value="14E390D5-2371-48B4-A9DE-2D35BC18E868" />
			<column name="name" value="Not an Early Alert Class" />
			<column name="description" value="Not an early alert class" />
			<column name="created_date" valueDate="2012-05-11T10:00:00" />
			<column name="modified_date" valueDate="2012-05-11T10:00:00" />
			<column name="created_by" value="58ba5ee3-734e-4ae9-b9c5-943774b4de41" />
			<column name="modified_by" value="58ba5ee3-734e-4ae9-b9c5-943774b4de41" />
			<column name="object_status" value="1" />
			<column name="sort_order" value="4" />
		</insert>
		<insert tableName="early_alert_outcome">
			<column name="id" value="D944D62E-0974-4058-85C7-E6B3D6159D73" />
			<column name="name" value="Duplicate Early Alert Notice" />
			<column name="description" value="Duplicate early alert notice" />
			<column name="created_date" valueDate="2012-05-11T10:00:00" />
			<column name="modified_date" valueDate="2012-05-11T10:00:00" />
			<column name="created_by" value="58ba5ee3-734e-4ae9-b9c5-943774b4de41" />
			<column name="modified_by" value="58ba5ee3-734e-4ae9-b9c5-943774b4de41" />
			<column name="object_status" value="1" />
			<column name="sort_order" value="5" />
		</insert>

		<rollback></rollback>
	</changeSet>

</databaseChangeLog>
    
